{"title": "bttv-emotes", "id": "bttv-emotes", "stickers": [{"body": "ApuBand", "url": "mxc://matrix.org/OPSoCWPJmwhtHFSkPqyuJqlz", "info": {"w": 112, "h": 112, "size": 12594, "mimetype": "image/png", "thumbnail_url": "mxc://matrix.org/OPSoCWPJmwhtHFSkPqyuJqlz", "thumbnail_info": {"w": 112, "h": 112, "size": 12594, "mimetype": "image/png"}}, "msgtype": "m.sticker", "id": "sha256:66a3b30965a624a1cbfbaa89cfa52dd539f38744b0564cb370f560f014ce30d6"}, {"body": "ApuDance", "url": "mxc://matrix.org/vHURhmdJMdIxCtsngaufUPlG", "info": {"w": 112, "h": 112, "size": 6833, "mimetype": "image/png", "thumbnail_url": "mxc://matrix.org/vHURhmdJMdIxCtsngaufUPlG", "thumbnail_info": {"w": 112, "h": 112, "size": 6833, "mimetype": "image/png"}}, "msgtype": "m.sticker", "id": "sha256:800b334e543241a172b56ee7d0f0237c64fcab6428f478166a658a0f9d86c049"}, {"body": "Copege", "url": "mxc://matrix.org/pIWDFqWZwShpMWkvFboeqKjP", "info": {"w": 112, "h": 112, "size": 13824, "mimetype": "image/png", "thumbnail_url": "mxc://matrix.org/pIWDFqWZwShpMWkvFboeqKjP", "thumbnail_info": {"w": 112, "h": 112, "size": 13824, "mimetype": "image/png"}}, "msgtype": "m.sticker", "id": "sha256:d7023257cbd5821f846576ac7e5e81cce1197cc42a97e49eb8fb36fd1c02bc4f"}, {"body": "PepeHands", "url": "mxc://matrix.org/dNBteMoaSnBnseiEiHYzUiSd", "info": {"w": 112, "h": 112, "size": 20935, "mimetype": "image/png", "thumbnail_url": "mxc://matrix.org/dNBteMoaSnBnseiEiHYzUiSd", "thumbnail_info": {"w": 112, "h": 112, "size": 20935, "mimetype": "image/png"}}, "msgtype": "m.sticker", "id": "sha256:09d9d241cf1cbf39daa2f2c6cef383af0f9fde581f0c2b0bed5a351bea3153a7"}, {"body": "PepeLaugh", "url": "mxc://matrix.org/sYekZcpNGxKVvJusssLGlKph", "info": {"w": 112, "h": 112, "size": 12759, "mimetype": "image/png", "thumbnail_url": "mxc://matrix.org/sYekZcpNGxKVvJusssLGlKph", "thumbnail_info": {"w": 112, "h": 112, "size": 12759, "mimetype": "image/png"}}, "msgtype": "m.sticker", "id": "sha256:32f4855ba3a89dacffd3940efde9e183c8963f6f8ac8d0830f0241f86b23b3ac"}, {"body": "PepePls", "url": "mxc://matrix.org/nprpAiLYvNSYKGPKnHVrfMIK", "info": {"w": 112, "h": 112, "size": 3775, "mimetype": "image/png", "thumbnail_url": "mxc://matrix.org/nprpAiLYvNSYKGPKnHVrfMIK", "thumbnail_info": {"w": 112, "h": 112, "size": 3775, "mimetype": "image/png"}}, "msgtype": "m.sticker", "id": "sha256:2de56f0d5948f644ee3a49a61593ae8d2ca43e579101d6c5ebf50eeff49f364b"}, {"body": "monkaS", "url": "mxc://matrix.org/kGCkJlPZUgluHbPOtjXVaGzp", "info": {"w": 112, "h": 112, "size": 21825, "mimetype": "image/png", "thumbnail_url": "mxc://matrix.org/kGCkJlPZUgluHbPOtjXVaGzp", "thumbnail_info": {"w": 112, "h": 112, "size": 21825, "mimetype": "image/png"}}, "msgtype": "m.sticker", "id": "sha256:f8c8411efa1065b43a4d1b0a1e948069845d9efd0362ac8194c3cfc1fefde3c6"}, {"body": "pepeJAM", "url": "mxc://matrix.org/PYganJhkczmjybRRMFTXJkbT", "info": {"w": 112, "h": 108, "size": 14398, "mimetype": "image/png", "thumbnail_url": "mxc://matrix.org/PYganJhkczmjybRRMFTXJkbT", "thumbnail_info": {"w": 112, "h": 108, "size": 14398, "mimetype": "image/png"}}, "msgtype": "m.sticker", "id": "sha256:6a91a492b3c4d0230ffac13672d99b03fa9587de25563398c07586ff0b2b5837"}]}